[{"refcode_short":"Outlook","refcode_long":"The Central Union Outlook","content":"The Central Union Outlook"},{"refcode_short":"Outlook February 18,  1913","refcode_long":"The Central Union Outlook February 18,  1913","content":"1913"},{"refcode_short":"Outlook February 18,  1913","refcode_long":"The Central Union Outlook February 18,  1913","content":"February 18, 1913"},{"refcode_short":"Outlook February 18,  1913","refcode_long":"The Central Union Outlook February 18,  1913","content":"A Delightful Time"},{"refcode_short":"Outlook February 18,  1913, par. 1","refcode_long":"The Central Union Outlook February 18,  1913, paragraph 1","content":"“Dear Brethren,”"}]